[
    {
        "title": "الاستغلال الأمثل لمواسم الطاعات | د. أحمد عبد المنعم",
        "url": "https://www.youtube.com/watch?v=SL2CdQ1cqKE&list=PLnpYU8_AiEPfvH4J5i52AjkIudjhOcTdL&index=1&pp=iAQB",
        "category": "شهر رمضان | د. أحمد عبد المنعم",
        "video_id": "SL2CdQ1cqKE",
        "thumbnail": "https://img.youtube.com/vi/SL2CdQ1cqKE/mqdefault.jpg",
        "playlist_id": "PLnpYU8_AiEPfvH4J5i52AjkIudjhOcTdL"
    },
    {
        "title": "١. إعادة تعريف | شهر رمضان الذي أنزل فيه القرآن | د. أحمد عبد المنعم",
        "url": "https://www.youtube.com/watch?v=7jTBtrcGcJ0&list=PLnpYU8_AiEPfvH4J5i52AjkIudjhOcTdL&index=2&pp=iAQB",
        "category": "شهر رمضان | د. أحمد عبد المنعم",
        "video_id": "7jTBtrcGcJ0",
        "thumbnail": "https://img.youtube.com/vi/7jTBtrcGcJ0/mqdefault.jpg",
        "playlist_id": "PLnpYU8_AiEPfvH4J5i52AjkIudjhOcTdL"
    },
    {
        "title": "٢. رمضان والقرآن | شهر رمضان الذي أنزل فيه القرآن | د. أحمد عبد المنعم",
        "url": "https://www.youtube.com/watch?v=Qai7B89yULQ&list=PLnpYU8_AiEPfvH4J5i52AjkIudjhOcTdL&index=3&pp=iAQB",
        "category": "شهر رمضان | د. أحمد عبد المنعم",
        "video_id": "Qai7B89yULQ",
        "thumbnail": "https://img.youtube.com/vi/Qai7B89yULQ/mqdefault.jpg",
        "playlist_id": "PLnpYU8_AiEPfvH4J5i52AjkIudjhOcTdL"
    },
    {
        "title": "٣. خطوات عملية | شهر رمضان الذي أنزل فيه القرآن | د. أحمد عبد المنعم",
        "url": "https://www.youtube.com/watch?v=r4kBVDimcTg&list=PLnpYU8_AiEPfvH4J5i52AjkIudjhOcTdL&index=4&pp=iAQB",
        "category": "شهر رمضان | د. أحمد عبد المنعم",
        "video_id": "r4kBVDimcTg",
        "thumbnail": "https://img.youtube.com/vi/r4kBVDimcTg/mqdefault.jpg",
        "playlist_id": "PLnpYU8_AiEPfvH4J5i52AjkIudjhOcTdL"
    },
    {
        "title": "القرآن في رمضان | د. أحمد عبد المنعم",
        "url": "https://www.youtube.com/watch?v=W8yr_et2CSI&list=PLnpYU8_AiEPfvH4J5i52AjkIudjhOcTdL&index=5&pp=iAQB",
        "category": "شهر رمضان | د. أحمد عبد المنعم",
        "video_id": "W8yr_et2CSI",
        "thumbnail": "https://img.youtube.com/vi/W8yr_et2CSI/mqdefault.jpg",
        "playlist_id": "PLnpYU8_AiEPfvH4J5i52AjkIudjhOcTdL"
    },
    {
        "title": "رمضان والقرآن | د. أحمد عبد المنعم",
        "url": "https://www.youtube.com/watch?v=HQDK4xGB4TA&list=PLnpYU8_AiEPfvH4J5i52AjkIudjhOcTdL&index=6&pp=iAQB",
        "category": "شهر رمضان | د. أحمد عبد المنعم",
        "video_id": "HQDK4xGB4TA",
        "thumbnail": "https://img.youtube.com/vi/HQDK4xGB4TA/mqdefault.jpg",
        "playlist_id": "PLnpYU8_AiEPfvH4J5i52AjkIudjhOcTdL"
    },
    {
        "title": "مراحل الارتباط بالقرآن الكريم في رمضان | د. أحمد عبد المنعم",
        "url": "https://www.youtube.com/watch?v=T-4c6a4rXO0&list=PLnpYU8_AiEPfvH4J5i52AjkIudjhOcTdL&index=7&pp=iAQB",
        "category": "شهر رمضان | د. أحمد عبد المنعم",
        "video_id": "T-4c6a4rXO0",
        "thumbnail": "https://img.youtube.com/vi/T-4c6a4rXO0/mqdefault.jpg",
        "playlist_id": "PLnpYU8_AiEPfvH4J5i52AjkIudjhOcTdL"
    },
    {
        "title": "الصوم جُنّة (لا تخرق صيامك) | خطبة | د. أحمد عبد المنعم",
        "url": "https://www.youtube.com/watch?v=j0SPVMbidCM&list=PLnpYU8_AiEPfvH4J5i52AjkIudjhOcTdL&index=8&pp=iAQB",
        "category": "شهر رمضان | د. أحمد عبد المنعم",
        "video_id": "j0SPVMbidCM",
        "thumbnail": "https://img.youtube.com/vi/j0SPVMbidCM/mqdefault.jpg",
        "playlist_id": "PLnpYU8_AiEPfvH4J5i52AjkIudjhOcTdL"
    },
    {
        "title": "فرحتان | خطبة | د. أحمد عبد المنعم",
        "url": "https://www.youtube.com/watch?v=Vy4_MRRkNME&list=PLnpYU8_AiEPfvH4J5i52AjkIudjhOcTdL&index=9&pp=iAQB",
        "category": "شهر رمضان | د. أحمد عبد المنعم",
        "video_id": "Vy4_MRRkNME",
        "thumbnail": "https://img.youtube.com/vi/Vy4_MRRkNME/mqdefault.jpg",
        "playlist_id": "PLnpYU8_AiEPfvH4J5i52AjkIudjhOcTdL"
    },
    {
        "title": "وإليك نسعى ونحفد (الاجتهاد في العشر الأواخر) | خطبة | د. أحمد عبد المنعم",
        "url": "https://www.youtube.com/watch?v=h0EL8ia7-SE&list=PLnpYU8_AiEPfvH4J5i52AjkIudjhOcTdL&index=10&pp=iAQB",
        "category": "شهر رمضان | د. أحمد عبد المنعم",
        "video_id": "h0EL8ia7-SE",
        "thumbnail": "https://img.youtube.com/vi/h0EL8ia7-SE/mqdefault.jpg",
        "playlist_id": "PLnpYU8_AiEPfvH4J5i52AjkIudjhOcTdL"
    },
    {
        "title": "ليلة فارقة | د. أحمد عبد المنعم",
        "url": "https://www.youtube.com/watch?v=Ch9FhlkQMhg&list=PLnpYU8_AiEPfvH4J5i52AjkIudjhOcTdL&index=11&pp=iAQB",
        "category": "شهر رمضان | د. أحمد عبد المنعم",
        "video_id": "Ch9FhlkQMhg",
        "thumbnail": "https://img.youtube.com/vi/Ch9FhlkQMhg/mqdefault.jpg",
        "playlist_id": "PLnpYU8_AiEPfvH4J5i52AjkIudjhOcTdL"
    },
    {
        "title": "من حكم الصيام (ولا تأكلوا أموالكم بينكم بالباطل) | خطبة | د. أحمد عبد المنعم",
        "url": "https://www.youtube.com/watch?v=S0bx18jdiac&list=PLnpYU8_AiEPfvH4J5i52AjkIudjhOcTdL&index=12&pp=iAQB",
        "category": "شهر رمضان | د. أحمد عبد المنعم",
        "video_id": "S0bx18jdiac",
        "thumbnail": "https://img.youtube.com/vi/S0bx18jdiac/mqdefault.jpg",
        "playlist_id": "PLnpYU8_AiEPfvH4J5i52AjkIudjhOcTdL"
    },
    {
        "title": "أيكم زادته هذه إيمانا (القرآن بعد رمضان) | د. أحمد عبد المنعم",
        "url": "https://www.youtube.com/watch?v=Tc4Qiw_Ir_I&list=PLnpYU8_AiEPfvH4J5i52AjkIudjhOcTdL&index=13&pp=iAQB",
        "category": "شهر رمضان | د. أحمد عبد المنعم",
        "video_id": "Tc4Qiw_Ir_I",
        "thumbnail": "https://img.youtube.com/vi/Tc4Qiw_Ir_I/mqdefault.jpg",
        "playlist_id": "PLnpYU8_AiEPfvH4J5i52AjkIudjhOcTdL"
    },
    {
        "title": "سلاسل الشيطان | خطبة | د. أحمد عبد المنعم",
        "url": "https://www.youtube.com/watch?v=_N3D1TUDb2A&list=PLnpYU8_AiEPfvH4J5i52AjkIudjhOcTdL&index=14&pp=iAQB",
        "category": "شهر رمضان | د. أحمد عبد المنعم",
        "video_id": "_N3D1TUDb2A",
        "thumbnail": "https://img.youtube.com/vi/_N3D1TUDb2A/mqdefault.jpg",
        "playlist_id": "PLnpYU8_AiEPfvH4J5i52AjkIudjhOcTdL"
    },
    {
        "title": "هو الله | د. أحمد عبد المنعم | 25 رمضان 1442",
        "url": "https://www.youtube.com/watch?v=0wGVYYrcbII&list=PLnpYU8_AiEPfvH4J5i52AjkIudjhOcTdL&index=15&pp=iAQB",
        "category": "شهر رمضان | د. أحمد عبد المنعم",
        "video_id": "0wGVYYrcbII",
        "thumbnail": "https://img.youtube.com/vi/0wGVYYrcbII/mqdefault.jpg",
        "playlist_id": "PLnpYU8_AiEPfvH4J5i52AjkIudjhOcTdL"
    },
    {
        "title": "وطعنوا في دينكم | د.أحمد عبدالمنعم | 10 رمضان 1442",
        "url": "https://www.youtube.com/watch?v=37N7xyTz6-M&list=PLnpYU8_AiEPfvH4J5i52AjkIudjhOcTdL&index=16&pp=iAQB",
        "category": "شهر رمضان | د. أحمد عبد المنعم",
        "video_id": "37N7xyTz6-M",
        "thumbnail": "https://img.youtube.com/vi/37N7xyTz6-M/mqdefault.jpg",
        "playlist_id": "PLnpYU8_AiEPfvH4J5i52AjkIudjhOcTdL"
    },
    {
        "title": "ولربك فاصبر | د. أحمد عبد المنعم | 26 رمضان 1442",
        "url": "https://www.youtube.com/watch?v=3Y28OB3_MMo&list=PLnpYU8_AiEPfvH4J5i52AjkIudjhOcTdL&index=17&pp=iAQB",
        "category": "شهر رمضان | د. أحمد عبد المنعم",
        "video_id": "3Y28OB3_MMo",
        "thumbnail": "https://img.youtube.com/vi/3Y28OB3_MMo/mqdefault.jpg",
        "playlist_id": "PLnpYU8_AiEPfvH4J5i52AjkIudjhOcTdL"
    },
    {
        "title": "رب إنهن أضللن كثيرا من الناس | د.أحمد عبدالمنعم | 13 رمضان 1442",
        "url": "https://www.youtube.com/watch?v=5JmY-kyq6ts&list=PLnpYU8_AiEPfvH4J5i52AjkIudjhOcTdL&index=18&pp=iAQB",
        "category": "شهر رمضان | د. أحمد عبد المنعم",
        "video_id": "5JmY-kyq6ts",
        "thumbnail": "https://img.youtube.com/vi/5JmY-kyq6ts/mqdefault.jpg",
        "playlist_id": "PLnpYU8_AiEPfvH4J5i52AjkIudjhOcTdL"
    },
    {
        "title": "ائت بقرآن غير هذا | د.أحمد عبدالمنعم | 11 رمضان 1442",
        "url": "https://www.youtube.com/watch?v=9gTyDUq068Y&list=PLnpYU8_AiEPfvH4J5i52AjkIudjhOcTdL&index=19&pp=iAQB",
        "category": "شهر رمضان | د. أحمد عبد المنعم",
        "video_id": "9gTyDUq068Y",
        "thumbnail": "https://img.youtube.com/vi/9gTyDUq068Y/mqdefault.jpg",
        "playlist_id": "PLnpYU8_AiEPfvH4J5i52AjkIudjhOcTdL"
    },
    {
        "title": "إنا أنزلنه في ليلة مباركة | د. أحمد عبد المنعم | 23 رمضان 1442",
        "url": "https://www.youtube.com/watch?v=RN_Osp-6wMA&list=PLnpYU8_AiEPfvH4J5i52AjkIudjhOcTdL&index=20&pp=iAQB",
        "category": "شهر رمضان | د. أحمد عبد المنعم",
        "video_id": "RN_Osp-6wMA",
        "thumbnail": "https://img.youtube.com/vi/RN_Osp-6wMA/mqdefault.jpg",
        "playlist_id": "PLnpYU8_AiEPfvH4J5i52AjkIudjhOcTdL"
    },
    {
        "title": "مشهد مهيب في خواتيم الواقعة | د. أحمد عبد المنعم | 24 رمضان 1442",
        "url": "https://www.youtube.com/watch?v=RmiYqJj5IA0&list=PLnpYU8_AiEPfvH4J5i52AjkIudjhOcTdL&index=21&pp=iAQB",
        "category": "شهر رمضان | د. أحمد عبد المنعم",
        "video_id": "RmiYqJj5IA0",
        "thumbnail": "https://img.youtube.com/vi/RmiYqJj5IA0/mqdefault.jpg",
        "playlist_id": "PLnpYU8_AiEPfvH4J5i52AjkIudjhOcTdL"
    },
    {
        "title": "أغير الله أتخذ وليّا | د.أحمد عبدالمنعم | 7 رمضان 1442",
        "url": "https://www.youtube.com/watch?v=S9sX-vK3qZE&list=PLnpYU8_AiEPfvH4J5i52AjkIudjhOcTdL&index=22&pp=iAQB",
        "category": "شهر رمضان | د. أحمد عبد المنعم",
        "video_id": "S9sX-vK3qZE",
        "thumbnail": "https://img.youtube.com/vi/S9sX-vK3qZE/mqdefault.jpg",
        "playlist_id": "PLnpYU8_AiEPfvH4J5i52AjkIudjhOcTdL"
    },
    {
        "title": "إنه كان صادق الوعد | د.أحمد عبدالمنعم | 16 رمضان 1442",
        "url": "https://www.youtube.com/watch?v=SSa7RnV1lrY&list=PLnpYU8_AiEPfvH4J5i52AjkIudjhOcTdL&index=23&pp=iAQB",
        "category": "شهر رمضان | د. أحمد عبد المنعم",
        "video_id": "SSa7RnV1lrY",
        "thumbnail": "https://img.youtube.com/vi/SSa7RnV1lrY/mqdefault.jpg",
        "playlist_id": "PLnpYU8_AiEPfvH4J5i52AjkIudjhOcTdL"
    },
    {
        "title": "سلوك أمة التوحيد في سورة النحل | د.أحمد عبدالمنعم | 14 رمضان 1442",
        "url": "https://www.youtube.com/watch?v=UK5nbzNv0vc&list=PLnpYU8_AiEPfvH4J5i52AjkIudjhOcTdL&index=24&pp=iAQB",
        "category": "شهر رمضان | د. أحمد عبد المنعم",
        "video_id": "UK5nbzNv0vc",
        "thumbnail": "https://img.youtube.com/vi/UK5nbzNv0vc/mqdefault.jpg",
        "playlist_id": "PLnpYU8_AiEPfvH4J5i52AjkIudjhOcTdL"
    },
    {
        "title": "أفصح مني لسانا | د. أحمد عبد المنعم | 21 مضان 1442",
        "url": "https://www.youtube.com/watch?v=YhQ9LQkFrAU&list=PLnpYU8_AiEPfvH4J5i52AjkIudjhOcTdL&index=25&pp=iAQB",
        "category": "شهر رمضان | د. أحمد عبد المنعم",
        "video_id": "YhQ9LQkFrAU",
        "thumbnail": "https://img.youtube.com/vi/YhQ9LQkFrAU/mqdefault.jpg",
        "playlist_id": "PLnpYU8_AiEPfvH4J5i52AjkIudjhOcTdL"
    },
    {
        "title": "فكيف إذا جئنا من كل أمة بشهيد | د.أحمد عبدالمنعم | 5 رمضان 1442",
        "url": "https://www.youtube.com/watch?v=aOUhoKorquQ&list=PLnpYU8_AiEPfvH4J5i52AjkIudjhOcTdL&index=26&pp=iAQB",
        "category": "شهر رمضان | د. أحمد عبد المنعم",
        "video_id": "aOUhoKorquQ",
        "thumbnail": "https://img.youtube.com/vi/aOUhoKorquQ/mqdefault.jpg",
        "playlist_id": "PLnpYU8_AiEPfvH4J5i52AjkIudjhOcTdL"
    },
    {
        "title": "سيقول السفهاء | د.أحمد عبدالمنعم | 2 رمضان 1442",
        "url": "https://www.youtube.com/watch?v=aVe-7ZuWtRk&list=PLnpYU8_AiEPfvH4J5i52AjkIudjhOcTdL&index=27&pp=iAQB",
        "category": "شهر رمضان | د. أحمد عبد المنعم",
        "video_id": "aVe-7ZuWtRk",
        "thumbnail": "https://img.youtube.com/vi/aVe-7ZuWtRk/mqdefault.jpg",
        "playlist_id": "PLnpYU8_AiEPfvH4J5i52AjkIudjhOcTdL"
    },
    {
        "title": "بداية قوية | د.أحمد عبدالمنعم | 1 رمضان 1442",
        "url": "https://www.youtube.com/watch?v=aq2sbCYDzg4&list=PLnpYU8_AiEPfvH4J5i52AjkIudjhOcTdL&index=28&pp=iAQB",
        "category": "شهر رمضان | د. أحمد عبد المنعم",
        "video_id": "aq2sbCYDzg4",
        "thumbnail": "https://img.youtube.com/vi/aq2sbCYDzg4/mqdefault.jpg",
        "playlist_id": "PLnpYU8_AiEPfvH4J5i52AjkIudjhOcTdL"
    },
    {
        "title": "فيدمغه | د.أحمد عبدالمنعم | 17 رمضان 1442",
        "url": "https://www.youtube.com/watch?v=gjIdUCXbdkc&list=PLnpYU8_AiEPfvH4J5i52AjkIudjhOcTdL&index=29&pp=iAQB",
        "category": "شهر رمضان | د. أحمد عبد المنعم",
        "video_id": "gjIdUCXbdkc",
        "thumbnail": "https://img.youtube.com/vi/gjIdUCXbdkc/mqdefault.jpg",
        "playlist_id": "PLnpYU8_AiEPfvH4J5i52AjkIudjhOcTdL"
    },
    {
        "title": "مجتمع سورة النور | د. أحمد عبدالمنعم | 20 رمضان 1442",
        "url": "https://www.youtube.com/watch?v=kxwaaWgWFQw&list=PLnpYU8_AiEPfvH4J5i52AjkIudjhOcTdL&index=30&pp=iAQB",
        "category": "شهر رمضان | د. أحمد عبد المنعم",
        "video_id": "kxwaaWgWFQw",
        "thumbnail": "https://img.youtube.com/vi/kxwaaWgWFQw/mqdefault.jpg",
        "playlist_id": "PLnpYU8_AiEPfvH4J5i52AjkIudjhOcTdL"
    },
    {
        "title": "فإن يخرجوا منها فإنا داخلون | د.أحمد عبدالمنعم | 6 رمضان 1442",
        "url": "https://www.youtube.com/watch?v=maLUvUGMQ2Q&list=PLnpYU8_AiEPfvH4J5i52AjkIudjhOcTdL&index=31&pp=iAQB",
        "category": "شهر رمضان | د. أحمد عبد المنعم",
        "video_id": "maLUvUGMQ2Q",
        "thumbnail": "https://img.youtube.com/vi/maLUvUGMQ2Q/mqdefault.jpg",
        "playlist_id": "PLnpYU8_AiEPfvH4J5i52AjkIudjhOcTdL"
    },
    {
        "title": "لا تلتفت | د.أحمد عبدالمنعم | 19 رمضان 1442",
        "url": "https://www.youtube.com/watch?v=oFh8ERWsgDc&list=PLnpYU8_AiEPfvH4J5i52AjkIudjhOcTdL&index=32&pp=iAQB",
        "category": "شهر رمضان | د. أحمد عبد المنعم",
        "video_id": "oFh8ERWsgDc",
        "thumbnail": "https://img.youtube.com/vi/oFh8ERWsgDc/mqdefault.jpg",
        "playlist_id": "PLnpYU8_AiEPfvH4J5i52AjkIudjhOcTdL"
    },
    {
        "title": "كنتم خير أمة | د.أحمد عبدالمنعم | 4 رمضان 1442",
        "url": "https://www.youtube.com/watch?v=on-UCCzsu-Y&list=PLnpYU8_AiEPfvH4J5i52AjkIudjhOcTdL&index=33&pp=iAQB",
        "category": "شهر رمضان | د. أحمد عبد المنعم",
        "video_id": "on-UCCzsu-Y",
        "thumbnail": "https://img.youtube.com/vi/on-UCCzsu-Y/mqdefault.jpg",
        "playlist_id": "PLnpYU8_AiEPfvH4J5i52AjkIudjhOcTdL"
    },
    {
        "title": "والله يريد الآخرة | د.أحمد عبدالمنعم | 9 رمضان 1442",
        "url": "https://www.youtube.com/watch?v=sxTGNcD3KDE&list=PLnpYU8_AiEPfvH4J5i52AjkIudjhOcTdL&index=34&pp=iAQB",
        "category": "شهر رمضان | د. أحمد عبد المنعم",
        "video_id": "sxTGNcD3KDE",
        "thumbnail": "https://img.youtube.com/vi/sxTGNcD3KDE/mqdefault.jpg",
        "playlist_id": "PLnpYU8_AiEPfvH4J5i52AjkIudjhOcTdL"
    },
    {
        "title": "أعداء الله | د.أحمد عبد المنعم | 22 رمضان 1442",
        "url": "https://www.youtube.com/watch?v=vxNxPzfuoSc&list=PLnpYU8_AiEPfvH4J5i52AjkIudjhOcTdL&index=35&pp=iAQB",
        "category": "شهر رمضان | د. أحمد عبد المنعم",
        "video_id": "vxNxPzfuoSc",
        "thumbnail": "https://img.youtube.com/vi/vxNxPzfuoSc/mqdefault.jpg",
        "playlist_id": "PLnpYU8_AiEPfvH4J5i52AjkIudjhOcTdL"
    },
    {
        "title": "لا تزغ قلوبنا وهب لنا من لدنك رحمة | د.أحمد عبدالمنعم | 3 رمضان 1442",
        "url": "https://www.youtube.com/watch?v=zAkqRTaRyaY&list=PLnpYU8_AiEPfvH4J5i52AjkIudjhOcTdL&index=36&pp=iAQB",
        "category": "شهر رمضان | د. أحمد عبد المنعم",
        "video_id": "zAkqRTaRyaY",
        "thumbnail": "https://img.youtube.com/vi/zAkqRTaRyaY/mqdefault.jpg",
        "playlist_id": "PLnpYU8_AiEPfvH4J5i52AjkIudjhOcTdL"
    },
    {
        "title": "ابكِ له بكاء التائه! | د.أحمد عبد المنعم",
        "url": "https://www.youtube.com/watch?v=nx2OMbZ9O2I&list=PLnpYU8_AiEPfvH4J5i52AjkIudjhOcTdL&index=37&pp=iAQB",
        "category": "شهر رمضان | د. أحمد عبد المنعم",
        "video_id": "nx2OMbZ9O2I",
        "thumbnail": "https://img.youtube.com/vi/nx2OMbZ9O2I/mqdefault.jpg",
        "playlist_id": "PLnpYU8_AiEPfvH4J5i52AjkIudjhOcTdL"
    }
]