[
  {
    "title": "#أمداد_قرآنية - سورة الفاتحة (1)",
    "url": "https://www.youtube.com/watch?v=wVwSBLoqtqs",
    "thumbnail": "https://i.ytimg.com/vi/wVwSBLoqtqs/mqdefault.jpg",
    "video_id": "wVwSBLoqtqs",
    "playlist_id": "PLQVX7_Rc0v0vKhq3BtbBmzenBxt8J5E7b"
  },
  {
    "title": "#أمداد_قرآنية - سورة الفاتحة (7)",
    "url": "https://www.youtube.com/watch?v=Q0FZhoROyNg",
    "thumbnail": "https://i.ytimg.com/vi/Q0FZhoROyNg/mqdefault.jpg",
    "video_id": "Q0FZhoROyNg",
    "playlist_id": "PLQVX7_Rc0v0vKhq3BtbBmzenBxt8J5E7b"
  },
  {
    "title": "#أمداد_قرآنية - سورة الفاتحة (6)",
    "url": "https://www.youtube.com/watch?v=ZBrR1VXdS28",
    "thumbnail": "https://i.ytimg.com/vi/ZBrR1VXdS28/mqdefault.jpg",
    "video_id": "ZBrR1VXdS28",
    "playlist_id": "PLQVX7_Rc0v0vKhq3BtbBmzenBxt8J5E7b"
  },
  {
    "title": "#أمداد_قرآنية - سورة الفاتحة (14)",
    "url": "https://www.youtube.com/watch?v=HA6XUqU3xUs",
    "thumbnail": "https://i.ytimg.com/vi/HA6XUqU3xUs/mqdefault.jpg",
    "video_id": "HA6XUqU3xUs",
    "playlist_id": "PLQVX7_Rc0v0vKhq3BtbBmzenBxt8J5E7b"
  },
  {
    "title": "#أمداد_قرآنية - سورة الفاتحة (13)",
    "url": "https://www.youtube.com/watch?v=HedhPgw6rJQ",
    "thumbnail": "https://i.ytimg.com/vi/HedhPgw6rJQ/mqdefault.jpg",
    "video_id": "HedhPgw6rJQ",
    "playlist_id": "PLQVX7_Rc0v0vKhq3BtbBmzenBxt8J5E7b"
  },
  {
    "title": "#أمداد_قرآنية - سورة الفاتحة (5)",
    "url": "https://www.youtube.com/watch?v=PuzSMRTRauY",
    "thumbnail": "https://i.ytimg.com/vi/PuzSMRTRauY/mqdefault.jpg",
    "video_id": "PuzSMRTRauY",
    "playlist_id": "PLQVX7_Rc0v0vKhq3BtbBmzenBxt8J5E7b"
  },
  {
    "title": "#أمداد_قرآنية - سورة الفاتحة (4)",
    "url": "https://www.youtube.com/watch?v=Aqd5qUqM5Js",
    "thumbnail": "https://i.ytimg.com/vi/Aqd5qUqM5Js/mqdefault.jpg",
    "video_id": "Aqd5qUqM5Js",
    "playlist_id": "PLQVX7_Rc0v0vKhq3BtbBmzenBxt8J5E7b"
  },
  {
    "title": "#أمداد_قرآنية - سورة الفاتحة (3)",
    "url": "https://www.youtube.com/watch?v=hg22EqCgoHE",
    "thumbnail": "https://i.ytimg.com/vi/hg22EqCgoHE/mqdefault.jpg",
    "video_id": "hg22EqCgoHE",
    "playlist_id": "PLQVX7_Rc0v0vKhq3BtbBmzenBxt8J5E7b"
  },
  {
    "title": "#أمداد_قرآنية - سورة الفاتحة (12)",
    "url": "https://www.youtube.com/watch?v=FL6g0bKAZf0",
    "thumbnail": "https://i.ytimg.com/vi/FL6g0bKAZf0/mqdefault.jpg",
    "video_id": "FL6g0bKAZf0",
    "playlist_id": "PLQVX7_Rc0v0vKhq3BtbBmzenBxt8J5E7b"
  },
  {
    "title": "#أمداد_قرآنية - سورة الفاتحة (2)",
    "url": "https://www.youtube.com/watch?v=yY3DTLCysHM",
    "thumbnail": "https://i.ytimg.com/vi/yY3DTLCysHM/mqdefault.jpg",
    "video_id": "yY3DTLCysHM",
    "playlist_id": "PLQVX7_Rc0v0vKhq3BtbBmzenBxt8J5E7b"
  },
  {
    "title": "#أمداد_قرآنية - سورة الفاتحة (8)",
    "url": "https://www.youtube.com/watch?v=_drI4hbXw5M",
    "thumbnail": "https://i.ytimg.com/vi/_drI4hbXw5M/mqdefault.jpg",
    "video_id": "_drI4hbXw5M",
    "playlist_id": "PLQVX7_Rc0v0vKhq3BtbBmzenBxt8J5E7b"
  },
  {
    "title": "#أمداد_قرآنية - سورة الفاتحة (9)",
    "url": "https://www.youtube.com/watch?v=zD7Pex6YHNE",
    "thumbnail": "https://i.ytimg.com/vi/zD7Pex6YHNE/mqdefault.jpg",
    "video_id": "zD7Pex6YHNE",
    "playlist_id": "PLQVX7_Rc0v0vKhq3BtbBmzenBxt8J5E7b"
  },
  {
    "title": "#أمداد_قرآنية - سورة الفاتحة (10)",
    "url": "https://www.youtube.com/watch?v=sQJqEc8VPG0",
    "thumbnail": "https://i.ytimg.com/vi/sQJqEc8VPG0/mqdefault.jpg",
    "video_id": "sQJqEc8VPG0",
    "playlist_id": "PLQVX7_Rc0v0vKhq3BtbBmzenBxt8J5E7b"
  },
  {
    "title": "#أمداد_قرآنية - سورة الفاتحة (11)",
    "url": "https://www.youtube.com/watch?v=9QFLv7P2TaI",
    "thumbnail": "https://i.ytimg.com/vi/9QFLv7P2TaI/mqdefault.jpg",
    "video_id": "9QFLv7P2TaI",
    "playlist_id": "PLQVX7_Rc0v0vKhq3BtbBmzenBxt8J5E7b"
  },
  {
    "title": "#أمداد_قرآنية - سورة الفاتحة (15)",
    "url": "https://www.youtube.com/watch?v=9hQdD6pTz4I",
    "thumbnail": "https://i.ytimg.com/vi/9hQdD6pTz4I/mqdefault.jpg",
    "video_id": "9hQdD6pTz4I",
    "playlist_id": "PLQVX7_Rc0v0vKhq3BtbBmzenBxt8J5E7b"
  }
]